piecelength/__init__.py
piecelength/__main__.py
piecelength/piecelength.py
tests/__init__.py
tests/test_piecelength.py
piecelength-1.2.dist-info/LICENSE
piecelength-1.2.dist-info/METADATA
piecelength-1.2.dist-info/WHEEL
piecelength-1.2.dist-info/entry_points.txt
piecelength-1.2.dist-info/top_level.txt
piecelength-1.2.dist-info/RECORD
