Metadata-Version: 2.1
Name: piecelength
Version: 1.2
Summary: '.torrent' metafile ideal piecelength for small file size calculator.
Author: alexpdev
Author-email: alexpdev@protonmail.com
License: BSD
Keywords: bittorrent,metafiles
Classifier: Operating System :: OS Independent
Classifier: Programming Language :: Python :: 3.5
Classifier: Programming Language :: Python :: 3.6
Classifier: Programming Language :: Python :: 3.7
Classifier: Programming Language :: Python :: 3.8
Classifier: Programming Language :: Python :: 3.9
Classifier: Programming Language :: Python :: 3.10
Classifier: Topic :: Software Development :: Libraries :: Python Modules
Classifier: License :: OSI Approved :: BSD License
License-File: LICENSE
